condition/__init__.py
condition/_condition.py
condition/_version.py
condition/sql.py
condition-1.0.8.dist-info/LICENSE
condition-1.0.8.dist-info/METADATA
condition-1.0.8.dist-info/WHEEL
condition-1.0.8.dist-info/top_level.txt
condition-1.0.8.dist-info/RECORD
