Metadata-Version: 2.1
Name: condition
Version: 1.0.8
Summary: A user friendly way to construct conditions for pandas dataframe query and sql
Home-page: https://gitlab.com/wyzhao/condition
Author: Weiyang Zhao
Author-email: wyzhao@gmail.com
License: UNKNOWN
Project-URL: Docs, https://condition.readthedocs.io/en/latest/
Project-URL: Source, https://gitlab.com/wyzhao/condition
Project-URL: Bug Reports/Issues, https://gitlab.com/wyzhao/condition/issues
Platform: UNKNOWN
Classifier: Development Status :: 4 - Beta
Classifier: Intended Audience :: Developers
Classifier: License :: OSI Approved :: MIT License
Classifier: Programming Language :: Python :: 3.6
Classifier: Programming Language :: Python :: 3.7
Classifier: Programming Language :: Python :: 3.8
Classifier: Programming Language :: Python :: 3.9
Classifier: Topic :: Software Development :: Libraries
Classifier: Topic :: Utilities
Requires-Dist: pandas
Requires-Dist: versioneer
Provides-Extra: all
Requires-Dist: jinja2 ; extra == 'all'
Requires-Dist: pandas ; extra == 'all'
Requires-Dist: black ; extra == 'all'
Requires-Dist: coverage ; extra == 'all'
Requires-Dist: pyarrow ; extra == 'all'
Requires-Dist: pytest ; extra == 'all'
Requires-Dist: pytest-cov ; extra == 'all'
Requires-Dist: prospector ; extra == 'all'
Requires-Dist: mypy ; extra == 'all'
Requires-Dist: sphinx ; extra == 'all'
Requires-Dist: ipython ; extra == 'all'
Requires-Dist: rst2pdf ; extra == 'all'
Requires-Dist: sphinx-rtd-theme ; extra == 'all'
Requires-Dist: graphviz ; extra == 'all'
Requires-Dist: sphinx-copybutton ; extra == 'all'
Requires-Dist: versioneer ; extra == 'all'
Provides-Extra: dev
Requires-Dist: pandas ; extra == 'dev'
Requires-Dist: black ; extra == 'dev'
Requires-Dist: coverage ; extra == 'dev'
Requires-Dist: jinja2 ; extra == 'dev'
Requires-Dist: pyarrow ; extra == 'dev'
Requires-Dist: pytest ; extra == 'dev'
Requires-Dist: pytest-cov ; extra == 'dev'
Requires-Dist: prospector ; extra == 'dev'
Requires-Dist: mypy ; extra == 'dev'
Requires-Dist: sphinx ; extra == 'dev'
Requires-Dist: ipython ; extra == 'dev'
Requires-Dist: rst2pdf ; extra == 'dev'
Requires-Dist: sphinx-rtd-theme ; extra == 'dev'
Requires-Dist: graphviz ; extra == 'dev'
Requires-Dist: sphinx-copybutton ; extra == 'dev'
Requires-Dist: versioneer ; extra == 'dev'
Provides-Extra: sql
Requires-Dist: jinja2 ; extra == 'sql'
